mxmapi/__init__.py
mxmapi/client.py
mxmapi/exceptions.py
mxmapi-0.1.2.dist-info/LICENSE
mxmapi-0.1.2.dist-info/METADATA
mxmapi-0.1.2.dist-info/WHEEL
mxmapi-0.1.2.dist-info/top_level.txt
mxmapi-0.1.2.dist-info/RECORD
