Metadata-Version: 2.1
Name: mxmapi
Version: 0.1.2
Summary: A simple Python library for the Musixmatch Web API
Home-page: https://mxmapi.readthedocs.io/
Author: Adel Hashem
Author-email: adel.mohamed.9998@gmail.com
License: MIT
Project-URL: Source, https://github.com/AdelHashem/mxmapi
License-File: LICENSE
Requires-Dist: requests (>=2.25.0)
Requires-Dist: urllib3 (>=1.26.0)
